woma/__init__.py
woma/main.py
woma/data/ANEOS_Fe85Si15_S20.txt
woma/data/ANEOS_forsterite_S19.txt
woma/data/ANEOS_iron_S20.txt
woma/data/AQUA_H20.txt
woma/data/CD21_HHe.txt
woma/data/CMS19_H.txt
woma/data/CMS19_He.txt
woma/data/HM80_HHe.txt
woma/data/HM80_ice.txt
woma/data/HM80_rock.txt
woma/data/SESAME_basalt_7530.txt
woma/data/SESAME_iron_2140.txt
woma/data/SESAME_water_7154.txt
woma/data/SS08_water.txt
woma/data/u_cold_array_HM80_ice.npy
woma/data/u_cold_array_HM80_rock.npy
woma/data/u_cold_array_Til_basalt.npy
woma/data/u_cold_array_Til_granite.npy
woma/data/u_cold_array_Til_iron.npy
woma/data/u_cold_array_Til_water.npy
woma/eos/T_rho.py
woma/eos/__init__.py
woma/eos/eos.py
woma/eos/generation.py
woma/eos/hm80.py
woma/eos/idg.py
woma/eos/sesame.py
woma/eos/tillotson.py
woma/misc/__init__.py
woma/misc/glob_vars.py
woma/misc/io.py
woma/misc/set_up.py
woma/misc/utils.py
woma/spherical_funcs/L1_spherical.py
woma/spherical_funcs/L2_spherical.py
woma/spherical_funcs/L3_spherical.py
woma/spherical_funcs/__init__.py
woma/spin_funcs/L1_spin.py
woma/spin_funcs/L2_spin.py
woma/spin_funcs/L3_spin.py
woma/spin_funcs/__init__.py
woma/spin_funcs/utils_spin.py
woma-1.4.4.dist-info/licenses/LICENSE.txt
woma-1.4.4.dist-info/METADATA
woma-1.4.4.dist-info/WHEEL
woma-1.4.4.dist-info/top_level.txt
woma-1.4.4.dist-info/RECORD
