Metadata-Version: 2.4
Name: woma
Version: 1.4.4
Summary: WorldMaker
Home-page: https://github.com/srbonilla/WoMa
Author: Sergio Ruiz-Bonilla, Jacob Kegerreis
Author-email: jacob.kegerreis@imperial.ac.uk
License: GNU GPLv3+
Project-URL: Paper, https://arxiv.org/abs/2007.02965
Project-URL: Group, http://icc.dur.ac.uk/giant_impacts
Project-URL: SEAGen, https://github.com/jkeger/seagen
Keywords: profile spinning rotating planet interior particle SPH initial conditions
Classifier: Programming Language :: Python :: 3
Classifier: License :: OSI Approved :: GNU General Public License v3 or later (GPLv3+)
Classifier: Development Status :: 4 - Beta
Requires-Python: >=3.8
License-File: LICENSE.txt
Requires-Dist: seagen>=1.5
Requires-Dist: numpy
Requires-Dist: numba>=0.50.1
Requires-Dist: h5py
Dynamic: author
Dynamic: author-email
Dynamic: classifier
Dynamic: description
Dynamic: description-content-type
Dynamic: home-page
Dynamic: keywords
Dynamic: license
Dynamic: license-file
Dynamic: project-url
Dynamic: requires-dist
Dynamic: requires-python
Dynamic: summary
